{"config": {"view": {"continuousWidth": 300, "continuousHeight": 300}}, "data": {"name": "data-13d91ca7a11a05ede6f57552be866b43"}, "mark": {"type": "bar"}, "encoding": {"color": {"field": "TRE", "type": "nominal"}, "tooltip": {"field": "OMOP_DESCR", "type": "nominal"}, "x": {"field": "Count", "type": "quantitative"}, "y": {"field": "OMOP", "sort": "-x", "type": "nominal"}}, "$schema": "https://vega.github.io/schema/vega-lite/v6.1.0.json", "datasets": {"data-13d91ca7a11a05ede6f57552be866b43": [{"OMOP": 4019097, "TRE": "Nottingham TRE 01", "Count": 49760.0, "OMOP_DESCR": "Molecular genetics procedure"}, {"OMOP": 4019097, "TRE": "Nottingham TRE 02", "Count": 49760.0, "OMOP_DESCR": "Molecular genetics procedure"}, {"OMOP": 3036277, "TRE": "Nottingham TRE 01", "Count": 49700.0, "OMOP_DESCR": "Body height"}, {"OMOP": 3036277, "TRE": "Nottingham TRE 02", "Count": 49720.0, "OMOP_DESCR": "Body height"}, {"OMOP": 3027018, "TRE": "Nottingham TRE 01", "Count": 49700.0, "OMOP_DESCR": "Heart rate"}, {"OMOP": 3027018, "TRE": "Nottingham TRE 02", "Count": 49720.0, "OMOP_DESCR": "Heart rate"}, {"OMOP": 3024171, "TRE": "Nottingham TRE 01", "Count": 49700.0, "OMOP_DESCR": "Respiratory rate"}, {"OMOP": 3024171, "TRE": "Nottingham TRE 02", "Count": 49720.0, "OMOP_DESCR": "Respiratory rate"}, {"OMOP": 3004249, "TRE": "Nottingham TRE 01", "Count": 49700.0, "OMOP_DESCR": "Systolic blood pressure"}, {"OMOP": 3004249, "TRE": "Nottingham TRE 02", "Count": 49720.0, "OMOP_DESCR": "Systolic blood pressure"}, {"OMOP": 3020891, "TRE": "Nottingham TRE 01", "Count": 49700.0, "OMOP_DESCR": "Body temperature"}, {"OMOP": 3020891, "TRE": "Nottingham TRE 02", "Count": 49720.0, "OMOP_DESCR": "Body temperature"}, {"OMOP": 3013762, "TRE": "Nottingham TRE 01", "Count": 49700.0, "OMOP_DESCR": "Body weight Measured"}, {"OMOP": 3013762, "TRE": "Nottingham TRE 02", "Count": 49720.0, "OMOP_DESCR": "Body weight Measured"}, {"OMOP": 3012888, "TRE": "Nottingham TRE 01", "Count": 49700.0, "OMOP_DESCR": "Diastolic blood pressure"}, {"OMOP": 3012888, "TRE": "Nottingham TRE 02", "Count": 49720.0, "OMOP_DESCR": "Diastolic blood pressure"}, {"OMOP": 4014829, "TRE": "Nottingham TRE 01", "Count": 49660.0, "OMOP_DESCR": "Consultation"}, {"OMOP": 4014829, "TRE": "Nottingham TRE 02", "Count": 49680.0, "OMOP_DESCR": "Consultation"}, {"OMOP": 2006977, "TRE": "Nottingham TRE 01", "Count": 49560.0, "OMOP_DESCR": "Interview and evaluation, described as limited"}, {"OMOP": 2006977, "TRE": "Nottingham TRE 02", "Count": 49590.0, "OMOP_DESCR": "Interview and evaluation, described as limited"}]}}